gadpytestprofiler/__init__.py
gadpytestprofiler/contextmanagers/__init__.py
gadpytestprofiler/contextmanagers/extensions/__init__.py
gadpytestprofiler/contextmanagers/extensions/psutils.py
gadpytestprofiler/contextmanagers/extensions/yappi.py
gadpytestprofiler/contextmanagers/python/__init__.py
gadpytestprofiler/contextmanagers/python/garbage.py
gadpytestprofiler/contextmanagers/python/time.py
gadpytestprofiler/contextmanagers/python/tracemalloc.py
gadpytestprofiler/models/__init__.py
gadpytestprofiler/models/extensions/__init__.py
gadpytestprofiler/models/extensions/postgres.py
gadpytestprofiler/models/extensions/psutils.py
gadpytestprofiler/models/extensions/sqlalchemy.py
gadpytestprofiler/models/extensions/yappi.py
gadpytestprofiler/models/profilers/__init__.py
gadpytestprofiler/models/profilers/extensions/__init__.py
gadpytestprofiler/models/profilers/extensions/sqlaclhemy.py
gadpytestprofiler/models/profilers/python/__init__.py
gadpytestprofiler/models/profilers/python/functions.py
gadpytestprofiler/models/python/__init__.py
gadpytestprofiler/models/python/garbage.py
gadpytestprofiler/models/python/statistics.py
gadpytestprofiler/models/python/tracemalloc.py
gadpytestprofiler/profilers/__init__.py
gadpytestprofiler/profilers/extensions/__init__.py
gadpytestprofiler/profilers/extensions/sqlaclhemy.py
gadpytestprofiler/profilers/python/__init__.py
gadpytestprofiler/profilers/python/functions.py
gadpytestprofiler/utils/__init__.py
gadpytestprofiler/utils/extensions/__init__.py
gadpytestprofiler/utils/extensions/postgres.py
gadpytestprofiler/utils/extensions/psutils.py
gadpytestprofiler/utils/extensions/sqlalchemy.py
gadpytestprofiler/utils/extensions/yappi.py
gadpytestprofiler/utils/python/__init__.py
gadpytestprofiler/utils/python/garbage.py
gadpytestprofiler/utils/python/statistics.py
gadpytestprofiler/utils/python/tracemalloc.py
tests/__init__.py
tests/test_init.py
gadpytestprofiler-0.0.1.dist-info/LICENSE
gadpytestprofiler-0.0.1.dist-info/METADATA
gadpytestprofiler-0.0.1.dist-info/WHEEL
gadpytestprofiler-0.0.1.dist-info/top_level.txt
gadpytestprofiler-0.0.1.dist-info/RECORD
