Metadata-Version: 2.1
Name: gadpytestprofiler
Version: 0.0.1
Summary: A profiler for benchmarking queries, functions, and I/O/network performance, with pydantic outputs.
Home-page: https://github.com/AlexDemure/gadpytestprofiler
Author: Alexander Grishchenko
Author-email: alexanderdemure@gmail.com
Classifier: Programming Language :: Python :: 3
Classifier: License :: OSI Approved :: MIT License
Classifier: Operating System :: OS Independent
Requires-Python: >=3.8
License-File: LICENSE
Requires-Dist: psutil
Requires-Dist: pydantic
Requires-Dist: sqlalchemy
Requires-Dist: yappi
